seurl/__init__.py
seurl/__main__.py
seurl/version.py
seurl-0.0.2.dist-info/LICENSE
seurl-0.0.2.dist-info/METADATA
seurl-0.0.2.dist-info/WHEEL
seurl-0.0.2.dist-info/entry_points.txt
seurl-0.0.2.dist-info/top_level.txt
seurl-0.0.2.dist-info/RECORD
