Metadata-Version: 2.1
Name: seurl
Version: 0.0.2
Summary: Retrieve domain URLs from Search Engines
Home-page: https://gitlab.com/Zer1t0/seurl
Author: Eloy Pérez González
Classifier: Programming Language :: Python :: 3
Classifier: License :: OSI Approved :: GNU General Public License v3 (GPLv3)
License-File: LICENSE
Requires-Dist: requests
Requires-Dist: bs4
